[{"Default":{"arrow":{"colors":{"activation":[255,0,0],"default":[255,255,255],"focus":[255,255,255]},"offset":10,"size":20},"border":{"colors":{"activation":[255,0,0],"default":[255,255,255],"focus":[255,255,255]},"corner_radius":10,"width":2},"fill_colors":{"activation":[155,155,155],"default":[0,0,0],"focus":[155,155,155]},"name":"Default","text":{"alignment":"CENTER","colors":{"activation":[255,0,0],"default":[255,255,255],"focus":[255,255,255]},"font":"Sans 40px","justify":true,"wrap":true,"x_offset":0,"y_offset":0}},"Style1":{"arrow":{"colors":{"activation":[255,0,0],"default":[255,255,255],"focus":[255,255,255]},"offset":10,"size":20},"border":{"colors":{"activation":[255,0,0],"default":[255,0,255],"focus":[255,255,255]},"corner_radius":10,"width":2},"fill_colors":{"activation":[155,155,155],"default":[0,0,0],"focus":[155,155,155]},"name":"Style1","text":{"alignment":"CENTER","colors":{"activation":[255,0,0],"default":[255,255,255],"focus":[255,255,255]},"font":"Sans 40px","justify":true,"wrap":true,"x_offset":0,"y_offset":0}},"Style2":{"arrow":{"colors":{"activation":[255,0,0],"default":[255,255,255],"focus":[255,255,255]},"offset":10,"size":20},"border":{"colors":{"activation":[255,0,0],"default":[255,255,255],"focus":[255,255,255]},"corner_radius":10,"width":10},"fill_colors":{"activation":[155,155,155],"default":[0,0,0],"focus":[155,155,155]},"name":"Style2","text":{"alignment":"CENTER","colors":{"activation":[255,0,0],"default":[255,255,255],"focus":[255,255,255]},"font":"Sans 40px","justify":true,"wrap":true,"x_offset":0,"y_offset":0}}}]